LICENSE
MANIFEST.in
README.md
pyproject.toml
setup.cfg
setup.py
djnotifier/__init__.py
djnotifier/apps.py
djnotifier/config.py
djnotifier/consumers.py
djnotifier/routing.py
djnotifier/utils.py
djnotifier.egg-info/PKG-INFO
djnotifier.egg-info/SOURCES.txt
djnotifier.egg-info/dependency_links.txt
djnotifier.egg-info/requires.txt
djnotifier.egg-info/top_level.txt
djnotifier/static/djnotifier/notification.js
djnotifier/static/djnotifier/notify.mp3
djnotifier/static/djnotifier/reconnecting-websocket.min.js
djnotifier/static/djnotifier/socket.js
djnotifier/static/djnotifier/notify/jquery.min.js
djnotifier/static/djnotifier/notify/notify.js
djnotifier/templates/djnotifier/core.html
docs/.DS_Store
docs/CUSTOMIZATION.md
docs/QUICK_START.md
docs/README.md
docs/USAGE_EXAMPLE.md
docs/assets/.DS_Store
docs/assets/usage_example/demo.gif
docs/assets/usage_example/ui.gif
example/__init__.py
example/admin.py
example/apps.py
example/urls.py
example/views.py